jangle/__about__.py
jangle/__init__.py
jangle/admin.py
jangle/apps.py
jangle/boot_django.py
jangle/dev_manage.py
jangle/lite.py
jangle/patterns.py
jangle/py.typed
jangle/readers.py
jangle/utils.py
jangle/views.py
jangle/management/__init__.py
jangle/management/commands/__init__.py
jangle/management/commands/loadjangledata.py
jangle/migrations/0001_initial.py
jangle/migrations/0002_rename_ext_data_regionsubtag_region.py
jangle/migrations/0003_alter_ianasubtagdescription_unique_together_and_more.py
jangle/migrations/__init__.py
jangle/models/__init__.py
jangle/models/languages.py
jangle/models/regions.py
jangle/models/scripts.py
jangle/models/tags.py
django_jangle-0.3a0.dist-info/METADATA
django_jangle-0.3a0.dist-info/WHEEL
django_jangle-0.3a0.dist-info/licenses/LICENSE.txt
django_jangle-0.3a0.dist-info/RECORD
