Metadata-Version: 2.1
Name: django-jangle
Version: 0.3a0
Summary: IETF BCP 47 / RFC 5646 language tags in Django
Project-URL: Homepage, https://github.com/egginabucket/jangle
Project-URL: Documentation, https://jangle.readthedocs.io/en/latest/
Author-email: Hannah Einstein <hannah.a.einstein@gmail.com>
License-File: LICENSE.txt
Keywords: django,iso 639,language tags,rfc 5646,rfc5646
Classifier: Framework :: Django :: 4.1
Classifier: License :: OSI Approved :: MIT License
Classifier: Operating System :: OS Independent
Classifier: Programming Language :: Python :: 3
Classifier: Programming Language :: Python :: 3 :: Only
Classifier: Programming Language :: Python :: 3.10
Classifier: Programming Language :: Python :: 3.11
Requires-Python: >=3.10
Requires-Dist: django>=4.1
Requires-Dist: requests>=2.28.0
Provides-Extra: dev
Requires-Dist: black; extra == 'dev'
Requires-Dist: django-stubs; extra == 'dev'
Requires-Dist: hatch; extra == 'dev'
Requires-Dist: ipython; extra == 'dev'
Requires-Dist: isort; extra == 'dev'
Requires-Dist: sphinx; extra == 'dev'
Requires-Dist: wheel; extra == 'dev'
